django_misc_helpers-0.1.12.dist-info/DESCRIPTION.rst
django_misc_helpers-0.1.12.dist-info/METADATA
django_misc_helpers-0.1.12.dist-info/RECORD
django_misc_helpers-0.1.12.dist-info/WHEEL
django_misc_helpers-0.1.12.dist-info/metadata.json
django_misc_helpers-0.1.12.dist-info/top_level.txt
djangohelpers/__init__.py
djangohelpers/edge.py
djangohelpers/images.py
djangohelpers/sqllog.py
djangohelpers/url.py
djangohelpers/utils.py
djangohelpers/data/AZ.txt
djangohelpers/data/azer.txt
djangohelpers/data/beeline.txt
djangohelpers/data/kievstar.txt
djangohelpers/data/megafon.txt
djangohelpers/data/mts.txt
djangohelpers/data/tele2.txt
