Metadata-Version: 2.0
Name: django-misc-helpers
Version: 0.1.12
Summary: Some django helpers
Home-page: https://bitbucket.org/pi11/django-misc-helpers
Author: pi11
Author-email: webii@yandex.ru
License: UNKNOWN
Platform: UNKNOWN
